DXPython_DVP/__init__.py
DXPython_DVP/core.py
dxpython_dvp-1.0.0.dist-info/licenses/LICENSE
dxpython_dvp-1.0.0.dist-info/METADATA
dxpython_dvp-1.0.0.dist-info/WHEEL
dxpython_dvp-1.0.0.dist-info/top_level.txt
dxpython_dvp-1.0.0.dist-info/RECORD
