Metadata-Version: 2.4
Name: DXPython_DVP
Version: 1.0.0
Summary: A DEXON DIVIP Python library
Home-page: https://github.com/yourusername/my_library
Author: Dexon Systems Ltd.
Author-email: sales@dexonsystems.com
Classifier: Programming Language :: Python :: 3
Classifier: License :: OSI Approved :: MIT License
Classifier: Operating System :: OS Independent
Requires-Python: >=3.0
License-File: LICENSE
Dynamic: author
Dynamic: author-email
Dynamic: classifier
Dynamic: description
Dynamic: description-content-type
Dynamic: home-page
Dynamic: license-file
Dynamic: requires-python
Dynamic: summary
